requests_asserts.py
requests_asserts-0.1.3.dist-info/LICENSE
requests_asserts-0.1.3.dist-info/WHEEL
requests_asserts-0.1.3.dist-info/METADATA
requests_asserts-0.1.3.dist-info/RECORD
