Metadata-Version: 2.1
Name: requests-asserts
Version: 0.1.3
Summary: The library to help test your HTTP requests using unittests
Home-page: https://github.com/ADR-007/requests-asserts
License: MIT
Keywords: mock,requests,unittests,tests,http
Author: Adrian Dankiv
Author-email: adr-007@ukr.net
Requires-Python: >=3.6,<4.0
Classifier: Development Status :: 4 - Beta
Classifier: License :: OSI Approved :: MIT License
Classifier: Programming Language :: Python :: 3
Classifier: Programming Language :: Python :: 3.6
Classifier: Programming Language :: Python :: 3.7
Classifier: Programming Language :: Python :: 3.8
Classifier: Programming Language :: Python :: 3.9
Classifier: Topic :: Internet :: WWW/HTTP
Classifier: Topic :: Software Development :: Testing
Classifier: Topic :: Software Development :: Testing :: Mocking
Classifier: Topic :: Software Development :: Testing :: Unit
Requires-Dist: requests (>=2.22,<3.0)
Requires-Dist: responses (>=0.14.0,<0.15.0)
Project-URL: Repository, https://github.com/ADR-007/requests-asserts
